[
  {
    "ingredientPattern": "KPL,PTP,SP_",
    "width": 3,
    "height": 3,
    "ingredients": {
      "K": {
        "type": "item",
        "code": "game:knife-*",
        "isTool": true,
        "toolDurabilityCost": 2
      },
      "S": {
        "type": "item",
        "code": "game:saw-*",
        "isTool": true,
        "toolDurabilityCost": 2
      },
      "L": {
        "type": "item",
        "code": "game:leather-normal-plain",
        "quantity": 2
      },
      "T": {
        "type": "item",
        "code": "game:flaxtwine",
        "quantity": 2
      },
      "P": {
        "type": "item",
        "code": "game:plank-*",
        "quantity": 1,
        "name": "wood",
        "skipVariants": [ "aged", "veryaged", "agedebony", "rottenebony", "crude" ]
      }
    },
    "output": {
      "type": "item",
      "code": "snowshoes-wooden-{wood}-plain-untreated"
    }
  }
]